setup.py
python_reuters.egg-info/PKG-INFO
python_reuters.egg-info/SOURCES.txt
python_reuters.egg-info/dependency_links.txt
python_reuters.egg-info/requires.txt
python_reuters.egg-info/top_level.txt
reuters/__init__.py
reuters/httpslib.py
reuters/utils.py