Metadata-Version: 1.0
Name: python-reuters
Version: 0.1
Summary: Python library to consume Reuters Soap Web services
Home-page: https://github.com/YACOWS/reuterslib
Author: Rael Max
Author-email: contato@raelmax.com
License: UNKNOWN
Platform: UNKNOWN
